enoki/__about__.py
enoki/__init__.py
enoki/enoki.py
enoki/testing.py
enoki-2.0.0.dist-info/METADATA
enoki-2.0.0.dist-info/WHEEL
enoki-2.0.0.dist-info/licenses/LICENSE
enoki-2.0.0.dist-info/RECORD
