Metadata-Version: 2.4
Name: enoki
Version: 2.0.0
Summary: A framework for creating and managing finite state machines (FSMs).
Author-email: Jeff Ciesielski <jeffciesielski@gmail.com>
License: MIT License
License-File: LICENSE
Classifier: License :: OSI Approved :: MIT License
Classifier: Operating System :: OS Independent
Classifier: Programming Language :: Python :: 3
Requires-Python: >=3.10
